Data Sheets/8-LINE TO 3-LINE/74148/v1.0/74148.vhd
library IEEE;
use IEEE.std_logic_1164.all;


entity data_74148 is
port(
	enable_input_inverted : in std_logic;
	data_input_inverted : in std_logic_vector ( 7 downto 0 );
	group_signal_inverted : out std_logic;
	data_output_inverted : out std_logic_vector ( 2 downto 0 );
	enable_output_inverted : out std_logic
);
end data_74148;

architecture chip of data_74148 is

begin
process(enable_input_inverted,data_input_inverted)
begin
	if enable_input_inverted = '1' then
		group_signal_inverted <= '1';
		data_output_inverted <= "111";
		enable_output_inverted <= '1';
	end if;
	if enable_input_inverted = '0' then
		if data_input_inverted = "11111111" then
			group_signal_inverted <= '1';
			data_output_inverted <= "111";
			enable_output_inverted <= '0';
		end if;
		if data_input_inverted(0) = '0' then
			group_signal_inverted <= '0';
			data_output_inverted <= "000";
			enable_output_inverted <= '1';
		elsif data_input_inverted(1) = '0' then
			group_signal_inverted <= '0';
			data_output_inverted <= "100";
			enable_output_inverted <= '1';

		elsif data_input_inverted(2) = '0' then
			group_signal_inverted <= '0';
			data_output_inverted <= "010";
			enable_output_inverted <= '1';

		elsif data_input_inverted(3) = '0' then
			group_signal_inverted <= '0';
			data_output_inverted <= "110";
			enable_output_inverted <= '1';

		elsif data_input_inverted(4) = '0' then
			group_signal_inverted <= '0';
			data_output_inverted <= "001";
			enable_output_inverted <= '1';

		elsif data_input_inverted(5) = '0' then
			group_signal_inverted <= '0';
			data_output_inverted <= "101";
			enable_output_inverted <= '1';

		elsif data_input_inverted(6) = '0' then
			group_signal_inverted <= '0';
			data_output_inverted <= "011";
			enable_output_inverted <= '1';

		elsif data_input_inverted(7) = '0' then
			group_signal_inverted <= '0';
			data_output_inverted <= "111";
			enable_output_inverted <= '1';
		end if;
	end if;
end process;
end chip;

Data Sheets/8-LINE TO 3-LINE/74148/v1.0/testbench.vhd
library IEEE;
use IEEE.std_logic_1164.all;

entity testbench is end;


architecture test of testbench is

signal i_enable_input, i_group_signal, i_enable_output : std_logic;
signal i_data_input : std_logic_vector ( 7 downto 0 ) := "00000000";
signal i_data_output : std_logic_vector ( 2 downto 0);

signal enable_input : std_logic := '1';
signal data_input : std_logic_vector ( 7 downto 0 ) := "11111111";

begin

UTT : entity work.data_74148 port map ( enable_input_inverted => i_enable_input, data_input_inverted => i_data_input, group_signal_inverted => i_group_signal, enable_output_inverted => i_enable_output, data_output_inverted => i_data_output);

estimulo : process
begin
	wait for 10 ns;
	i_enable_input <= '1';
	i_data_input <= "10110111";
	enable_input <= not i_enable_input;
	data_input <= not i_data_input;
	wait for 10 ns;
	i_enable_input <= '0';
	i_data_input <= "00000000";
	enable_input <= not i_enable_input;
	data_input <= not i_data_input;
	wait for 10 ns;
	i_enable_input <= '0';
	i_data_input <= "00000001";
	enable_input <= not i_enable_input;
	data_input <= not i_data_input;
	wait for 10 ns;
	i_enable_input <= '0';
	i_data_input <= "00000011";
	enable_input <= not i_enable_input;
	data_input <= not i_data_input;
	wait for 10 ns;
	i_enable_input <= '0';
	i_data_input <= "00000111";
	enable_input <= not i_enable_input;
	data_input <= not i_data_input;
	wait for 10 ns;
	i_enable_input <= '0';
	i_data_input <= "00001111";
	enable_input <= not i_enable_input;
	data_input <= not i_data_input;
	wait for 10 ns;
	i_enable_input <= '0';
	i_data_input <= "00011111";
	enable_input <= not i_enable_input;
	data_input <= not i_data_input;
	wait for 10 ns;
	i_enable_input <= '0';
	i_data_input <= "00111111";
	enable_input <= not i_enable_input;
	data_input <= not i_data_input;
	wait for 10 ns;
	i_enable_input <= '0';
	i_data_input <= "01111111";
	enable_input <= not i_enable_input;
	data_input <= not i_data_input;
	wait for 10 ns;
	i_enable_input <= '0';
	i_data_input <= "01001110";
	enable_input <= not i_enable_input;
	data_input <= not i_data_input;
	wait for 10 ns;
	i_enable_input <= '0';
	i_data_input <= "11111111";
	enable_input <= not i_enable_input;
	data_input <= not i_data_input;
	wait for 10 ns;
	--clear
	i_enable_input <= '0';
	i_data_input <= "00000000";
	enable_input <= not i_enable_input;
	data_input <= not i_data_input;
	wait;
end process;
end test;

Data Sheets/8-LINE TO 3-LINE/74148/v1.0/74148.vcd
$date
  Wed Jul 21 00:48:03 2021
$end
$version
  GHDL v0
$end
$timescale
  1 fs
$end
$scope module standard $end
$upscope $end
$scope module std_logic_1164 $end
$upscope $end
$scope module testbench $end
$var reg 1 ! i_enable_input $end
$var reg 1 " i_group_signal $end
$var reg 1 # i_enable_output $end
$var reg 8 $ i_data_input[7:0] $end
$var reg 3 % i_data_output[2:0] $end
$var reg 1 & enable_input $end
$var reg 8 ' data_input[7:0] $end
$scope module utt $end
$var reg 1 ( enable_input_inverted $end
$var reg 8 ) data_input_inverted[7:0] $end
$var reg 1 * group_signal_inverted $end
$var reg 3 + data_output_inverted[2:0] $end
$var reg 1 , enable_output_inverted $end
$upscope $end
$upscope $end
$enddefinitions $end
#0
U!
U"
U#
b00000000 $
bUUU %
1&
b11111111 '
U(
b00000000 )
U*
bUUU +
U,
#10000000
1!
1"
1#
b10110111 $
b111 %
U&
1(
b10110111 )
1*
b111 +
1,
#20000000
0!
0"
b00000000 $
b000 %
0&
b01001000 '
0(
b00000000 )
0*
b000 +
#30000000
b00000001 $
b100 %
1&
b11111111 '
b00000001 )
b100 +
#40000000
b00000011 $
b010 %
b11111110 '
b00000011 )
b010 +
#50000000
b00000111 $
b110 %
b11111100 '
b00000111 )
b110 +
#60000000
b00001111 $
b001 %
b11111000 '
b00001111 )
b001 +
#70000000
b00011111 $
b101 %
b11110000 '
b00011111 )
b101 +
#80000000
b00111111 $
b011 %
b11100000 '
b00111111 )
b011 +
#90000000
b01111111 $
b111 %
b11000000 '
b01111111 )
b111 +
#100000000
b01001110 $
b000 %
b10000000 '
b01001110 )
b000 +
#110000000
1"
0#
b11111111 $
b111 %
b10110001 '
b11111111 )
1*
b111 +
0,
#120000000
0"
1#
b00000000 $
b000 %
b00000000 '
b00000000 )
0*
b000 +
1,
